gfinancelib/__init__.py
gfinancelib/main.py
gfinancelib-1.535.dist-info/METADATA
gfinancelib-1.535.dist-info/WHEEL
gfinancelib-1.535.dist-info/top_level.txt
gfinancelib-1.535.dist-info/RECORD
