Metadata-Version: 2.1
Name: gfinancelib
Version: 1.535
Requires-Dist: pandas<=2.2.3
Requires-Dist: requests<=2.32.3
Requires-Dist: ta<=0.11.0
Requires-Dist: yfinance<=0.2.50
